<?xml version='1.0' encoding='UTF-8' standalone='no'?>
<sbml xmlns="http://www.sbml.org/sbml/level3/version1/core" level="3" version="1">
  <notes>
    <body xmlns="http://www.w3.org/1999/xhtml">
     <p>Exported by VCell 7.3</p>
  </body>
  </notes>
  <model areaUnits="um2" extentUnits="molecules" id="Greenwald_MIMB_2012___Fit_1_Application0" lengthUnits="um" name="Greenwald MIMB 2012 - Fit 1_Application0" substanceUnits="molecules" timeUnits="s" volumeUnits="um3">
    <listOfUnitDefinitions>
      <unitDefinition id="molecules">
        <listOfUnits>
          <unit exponent="1" kind="item" multiplier="1" scale="0"/>
        </listOfUnits>
      </unitDefinition>
      <unitDefinition id="um3">
        <listOfUnits>
          <unit exponent="3" kind="metre" multiplier="1" scale="-6"/>
        </listOfUnits>
      </unitDefinition>
      <unitDefinition id="um2">
        <listOfUnits>
          <unit exponent="2" kind="metre" multiplier="1" scale="-6"/>
        </listOfUnits>
      </unitDefinition>
      <unitDefinition id="um">
        <listOfUnits>
          <unit exponent="1" kind="metre" multiplier="1" scale="-6"/>
        </listOfUnits>
      </unitDefinition>
      <unitDefinition id="s">
        <listOfUnits>
          <unit exponent="1" kind="second" multiplier="1" scale="0"/>
        </listOfUnits>
      </unitDefinition>
      <unitDefinition id="_one_">
        <listOfUnits>
          <unit exponent="1" kind="dimensionless" multiplier="1" scale="0"/>
        </listOfUnits>
      </unitDefinition>
      <unitDefinition id="K">
        <listOfUnits>
          <unit exponent="1" kind="kelvin" multiplier="1" scale="0"/>
        </listOfUnits>
      </unitDefinition>
      <unitDefinition id="C_mol_1">
        <listOfUnits>
          <unit exponent="1" kind="coulomb" multiplier="1" scale="0"/>
          <unit exponent="-1" kind="mole" multiplier="1" scale="0"/>
        </listOfUnits>
      </unitDefinition>
      <unitDefinition id="C_nmol_1">
        <listOfUnits>
          <unit exponent="1" kind="coulomb" multiplier="1" scale="0"/>
          <unit exponent="-1" kind="mole" multiplier="1" scale="-9"/>
        </listOfUnits>
      </unitDefinition>
      <unitDefinition id="molecules_pmol_1">
        <listOfUnits>
          <unit exponent="1" kind="item" multiplier="1" scale="0"/>
          <unit exponent="-1" kind="mole" multiplier="1" scale="-12"/>
        </listOfUnits>
      </unitDefinition>
      <unitDefinition id="_one_000000000">
        <listOfUnits>
          <unit exponent="1" kind="dimensionless" multiplier="1000000000" scale="0"/>
        </listOfUnits>
      </unitDefinition>
      <unitDefinition id="mV_C_K_1_mol_1">
        <listOfUnits>
          <unit exponent="1" kind="volt" multiplier="1" scale="-3"/>
          <unit exponent="1" kind="coulomb" multiplier="1" scale="0"/>
          <unit exponent="-1" kind="kelvin" multiplier="1" scale="0"/>
          <unit exponent="-1" kind="mole" multiplier="1" scale="0"/>
        </listOfUnits>
      </unitDefinition>
      <unitDefinition id="mV_V_1">
        <listOfUnits>
          <unit exponent="1" kind="dimensionless" multiplier="1" scale="0"/>
        </listOfUnits>
      </unitDefinition>
      <unitDefinition id="uM_um3_molecules_1">
        <listOfUnits>
          <unit exponent="1" kind="mole" multiplier="1" scale="-6"/>
          <unit exponent="-1" kind="litre" multiplier="1" scale="0"/>
          <unit exponent="3" kind="metre" multiplier="1" scale="-6"/>
          <unit exponent="-1" kind="item" multiplier="1" scale="0"/>
        </listOfUnits>
      </unitDefinition>
      <unitDefinition id="uM">
        <listOfUnits>
          <unit exponent="1" kind="mole" multiplier="1" scale="-6"/>
          <unit exponent="-1" kind="litre" multiplier="1" scale="0"/>
        </listOfUnits>
      </unitDefinition>
      <unitDefinition id="s_1">
        <listOfUnits>
          <unit exponent="-1" kind="second" multiplier="1" scale="0"/>
        </listOfUnits>
      </unitDefinition>
      <unitDefinition id="uM_s_1">
        <listOfUnits>
          <unit exponent="1" kind="mole" multiplier="1" scale="-6"/>
          <unit exponent="-1" kind="litre" multiplier="1" scale="0"/>
          <unit exponent="-1" kind="second" multiplier="1" scale="0"/>
        </listOfUnits>
      </unitDefinition>
      <unitDefinition id="um3_s_1_molecules_1">
        <listOfUnits>
          <unit exponent="3" kind="metre" multiplier="1" scale="-6"/>
          <unit exponent="-1" kind="second" multiplier="1" scale="0"/>
          <unit exponent="-1" kind="item" multiplier="1" scale="0"/>
        </listOfUnits>
      </unitDefinition>
      <unitDefinition id="molecules_um_3">
        <listOfUnits>
          <unit exponent="1" kind="item" multiplier="1" scale="0"/>
          <unit exponent="-3" kind="metre" multiplier="1" scale="-6"/>
        </listOfUnits>
      </unitDefinition>
      <unitDefinition id="molecules_um_3_s_1">
        <listOfUnits>
          <unit exponent="1" kind="item" multiplier="1" scale="0"/>
          <unit exponent="-3" kind="metre" multiplier="1" scale="-6"/>
          <unit exponent="-1" kind="second" multiplier="1" scale="0"/>
        </listOfUnits>
      </unitDefinition>
      <unitDefinition id="uM_1_s_1">
        <listOfUnits>
          <unit exponent="-1" kind="mole" multiplier="1" scale="-6"/>
          <unit exponent="1" kind="litre" multiplier="1" scale="0"/>
          <unit exponent="-1" kind="second" multiplier="1" scale="0"/>
        </listOfUnits>
      </unitDefinition>
    </listOfUnitDefinitions>
    <listOfCompartments>
      <compartment constant="true" id="Extra_Cellular" name="Extra Cellular" size="50000" spatialDimensions="3" units="um3"/>
      <compartment constant="true" id="cytosol" name="cytosol" size="5000" spatialDimensions="3" units="um3"/>
      <compartment constant="true" id="Membrane" name="Membrane" size="1414" spatialDimensions="2" units="um2"/>
    </listOfCompartments>
    <listOfSpecies>
      <species boundaryCondition="false" compartment="cytosol" constant="false" hasOnlySubstanceUnits="true" id="cAMP" initialAmount="0" substanceUnits="molecules"/>
      <species boundaryCondition="false" compartment="cytosol" constant="false" hasOnlySubstanceUnits="true" id="AKAR" initialAmount="3.76383861875E6" substanceUnits="molecules"/>
      <species boundaryCondition="false" compartment="cytosol" constant="false" hasOnlySubstanceUnits="true" id="AC" initialAmount="1.5055354475E5" substanceUnits="molecules"/>
      <species boundaryCondition="false" compartment="cytosol" constant="false" hasOnlySubstanceUnits="true" id="RC" initialAmount="3.0110708949999996E6" substanceUnits="molecules"/>
      <species boundaryCondition="false" compartment="cytosol" constant="false" hasOnlySubstanceUnits="true" id="A2R" initialAmount="0" substanceUnits="molecules"/>
      <species boundaryCondition="false" compartment="cytosol" constant="false" hasOnlySubstanceUnits="true" id="PDE" initialAmount="4.2154992529999996E4" substanceUnits="molecules"/>
      <species boundaryCondition="false" compartment="cytosol" constant="false" hasOnlySubstanceUnits="true" id="ARC" initialAmount="0" substanceUnits="molecules"/>
      <species boundaryCondition="false" compartment="cytosol" constant="false" hasOnlySubstanceUnits="true" id="ICUE_cAMP" initialAmount="0" substanceUnits="molecules"/>
      <species boundaryCondition="false" compartment="cytosol" constant="false" hasOnlySubstanceUnits="true" id="A2RC" initialAmount="0" substanceUnits="molecules"/>
      <species boundaryCondition="false" compartment="cytosol" constant="false" hasOnlySubstanceUnits="true" id="AKARp" initialAmount="0" substanceUnits="molecules"/>
      <species boundaryCondition="false" compartment="cytosol" constant="false" hasOnlySubstanceUnits="true" id="ICUE" initialAmount="4.5166063424999994E5" substanceUnits="molecules"/>
      <species boundaryCondition="false" compartment="cytosol" constant="false" hasOnlySubstanceUnits="true" id="PKAC" initialAmount="0" substanceUnits="molecules"/>
    </listOfSpecies>
    <listOfParameters>
      <parameter constant="false" id="ICUE_ratio" units="_one_"/>
      <parameter constant="false" id="AKAR_ratio" units="_one_"/>
      <parameter constant="true" id="_T_" units="K" value="300"/>
      <parameter constant="true" id="_PI_" units="_one_" value="3.141592653589793"/>
      <parameter constant="true" id="_F_" units="C_mol_1" value="9.64853321E4"/>
      <parameter constant="true" id="_F_nmol_" units="C_nmol_1" value="9.64853321E-5"/>
      <parameter constant="true" id="_N_pmol_" units="molecules_pmol_1" value="6.02214179E11"/>
      <parameter constant="true" id="_K_GHK_" units="_one_000000000" value="1E-9"/>
      <parameter constant="true" id="_R_" units="mV_C_K_1_mol_1" value="8314.46261815"/>
      <parameter constant="true" id="K_millivolts_per_volt" units="mV_V_1" value="1000"/>
      <parameter constant="true" id="KMOLE" units="uM_um3_molecules_1" value="0.001660538783162726"/>
      <parameter constant="true" id="Km_cAMP_synth" units="uM" value="860"/>
      <parameter constant="true" id="ATP_cAMP_synth" units="uM" value="5000"/>
      <parameter constant="true" id="Km_Iso_cAMP_synth" units="uM" value="315"/>
      <parameter constant="true" id="kcat_iso_cAMP_synth" units="s_1" value="0.200273"/>
      <parameter constant="true" id="Kd_iso_cAMP_synth" units="uM" value="0.1"/>
      <parameter constant="true" id="kfsk_cAMP_synth" units="s_1" value="25.0451"/>
      <parameter constant="true" id="Iso_stim_cAMP_synth" units="uM" value="1"/>
      <parameter constant="true" id="t_iso_cAMP_synth" units="s" value="200"/>
      <parameter constant="true" id="Kd_fsk_cAMP_synth" units="uM" value="860"/>
      <parameter constant="true" id="FSK_stim_cAMP_synth" units="uM" value="50"/>
      <parameter constant="true" id="t_FSK_cAMP_synth" units="s" value="600"/>
      <parameter constant="false" id="Vmax_cAMP_synth" units="uM_s_1"/>
      <parameter constant="false" id="Vmax_Iso_cAMP_synth" units="uM_s_1"/>
      <parameter constant="false" id="AC_iso_cAMP_synth" units="uM"/>
      <parameter constant="false" id="Iso_cAMP_synth" units="uM"/>
      <parameter constant="false" id="AC_fsk_cAMP_synth" units="uM"/>
      <parameter constant="false" id="Fsk_cAMP_synth" units="uM"/>
      <parameter constant="true" id="Kf_PKA_act" units="s_1" value="4375"/>
      <parameter constant="true" id="Kr_PKA_act" units="um3_s_1_molecules_1" value="1.6605387831627259"/>
      <parameter constant="true" id="Km_cAMP_deg" units="molecules_um_3" value="785.8895035949998"/>
      <parameter constant="true" id="kcat_cAMP_deg" units="s_1" value="5"/>
      <parameter constant="true" id="Ki_cAMP_deg" units="uM" value="30"/>
      <parameter constant="true" id="t_IBMX_cAMP_deg" units="s" value="600"/>
      <parameter constant="true" id="IBMX_stim_cAMP_deg" units="uM" value="100"/>
      <parameter constant="false" id="Vmax_cAMP_deg" units="molecules_um_3_s_1"/>
      <parameter constant="false" id="PDE_avail_cAMP_deg" units="uM"/>
      <parameter constant="false" id="IBMX_cAMP_deg" units="uM"/>
      <parameter constant="true" id="Kf_PKA_bind1" units="um3_s_1_molecules_1" value="1.6605387831627259"/>
      <parameter constant="true" id="Kr_PKA_bind1" units="s_1" value="9140"/>
      <parameter constant="true" id="kcat_AKAR_dephos" units="uM_1_s_1" value="8.5"/>
      <parameter constant="true" id="PPase_AKAR_dephos" units="uM" value="2.14"/>
      <parameter constant="true" id="Kf_PKA_bind2" units="um3_s_1_molecules_1" value="1.6605387831627259"/>
      <parameter constant="true" id="Kr_PKA_bind2" units="s_1" value="1640"/>
      <parameter constant="true" id="Kf_ICUE_bind" units="um3_s_1_molecules_1" value="0.056805869394848635"/>
      <parameter constant="true" id="Kr_ICUE_bind" units="s_1" value="10"/>
      <parameter constant="true" id="Km_AKAR_phos" units="molecules_um_3" value="1.2646497758999998E4"/>
      <parameter constant="true" id="kcat_AKAR_phos" units="s_1" value="54"/>
      <parameter constant="false" id="Vmax_AKAR_phos" units="molecules_um_3_s_1"/>
    </listOfParameters>
    <listOfRules>
      <assignmentRule variable="ICUE_ratio">
        <math xmlns="http://www.w3.org/1998/Math/MathML">        
          <apply>
            <divide/>
            <apply>
              <times/>
              <cn> 0.0016605387831627259 </cn>
              <ci> ICUE_cAMP </ci>
            </apply>
            <apply>
              <plus/>
              <apply>
                <times/>
                <cn> 0.0016605387831627259 </cn>
                <ci> ICUE </ci>
              </apply>
              <apply>
                <times/>
                <cn> 0.0016605387831627259 </cn>
                <ci> ICUE_cAMP </ci>
              </apply>
            </apply>
          </apply>
        </math>
            </assignmentRule>
      <assignmentRule variable="AKAR_ratio">
        <math xmlns="http://www.w3.org/1998/Math/MathML">        
          <apply>
            <divide/>
            <apply>
              <times/>
              <cn> 0.0016605387831627259 </cn>
              <ci> AKARp </ci>
            </apply>
            <apply>
              <plus/>
              <apply>
                <times/>
                <cn> 0.0016605387831627259 </cn>
                <ci> AKAR </ci>
              </apply>
              <apply>
                <times/>
                <cn> 0.0016605387831627259 </cn>
                <ci> AKARp </ci>
              </apply>
            </apply>
          </apply>
        </math>
            </assignmentRule>
      <assignmentRule variable="Vmax_cAMP_synth">
        <math xmlns="http://www.w3.org/1998/Math/MathML">        
          <apply>
            <times/>
            <ci> kfsk_cAMP_synth </ci>
            <ci> AC_fsk_cAMP_synth </ci>
          </apply>
        </math>
            </assignmentRule>
      <assignmentRule variable="Vmax_Iso_cAMP_synth">
        <math xmlns="http://www.w3.org/1998/Math/MathML">        
          <apply>
            <times/>
            <ci> kcat_iso_cAMP_synth </ci>
            <ci> AC_iso_cAMP_synth </ci>
          </apply>
        </math>
            </assignmentRule>
      <assignmentRule variable="AC_iso_cAMP_synth">
        <math xmlns="http://www.w3.org/1998/Math/MathML">        
          <apply>
            <divide/>
            <apply>
              <times/>
              <apply>
                <times/>
                <cn> 0.0016605387831627259 </cn>
                <ci> AC </ci>
              </apply>
              <ci> Iso_cAMP_synth </ci>
            </apply>
            <apply>
              <plus/>
              <ci> Kd_iso_cAMP_synth </ci>
              <ci> Iso_cAMP_synth </ci>
            </apply>
          </apply>
        </math>
            </assignmentRule>
      <assignmentRule variable="Iso_cAMP_synth">
        <math xmlns="http://www.w3.org/1998/Math/MathML">        
          <apply>
            <times/>
            <ci> Iso_stim_cAMP_synth </ci>
            <apply>
              <gt/>
              <ci> t </ci>
              <ci> t_iso_cAMP_synth </ci>
            </apply>
          </apply>
        </math>
            </assignmentRule>
      <assignmentRule variable="AC_fsk_cAMP_synth">
        <math xmlns="http://www.w3.org/1998/Math/MathML">        
          <apply>
            <divide/>
            <apply>
              <times/>
              <apply>
                <times/>
                <cn> 0.0016605387831627259 </cn>
                <ci> AC </ci>
              </apply>
              <ci> Fsk_cAMP_synth </ci>
            </apply>
            <apply>
              <plus/>
              <ci> Kd_fsk_cAMP_synth </ci>
              <ci> Fsk_cAMP_synth </ci>
            </apply>
          </apply>
        </math>
            </assignmentRule>
      <assignmentRule variable="Fsk_cAMP_synth">
        <math xmlns="http://www.w3.org/1998/Math/MathML">        
          <apply>
            <times/>
            <ci> FSK_stim_cAMP_synth </ci>
            <apply>
              <gt/>
              <ci> t </ci>
              <ci> t_FSK_cAMP_synth </ci>
            </apply>
          </apply>
        </math>
            </assignmentRule>
      <assignmentRule variable="Vmax_cAMP_deg">
        <math xmlns="http://www.w3.org/1998/Math/MathML">        
          <apply>
            <times/>
            <apply>
              <times/>
              <cn> 602.214179 </cn>
              <ci> kcat_cAMP_deg </ci>
            </apply>
            <ci> PDE_avail_cAMP_deg </ci>
          </apply>
        </math>
            </assignmentRule>
      <assignmentRule variable="PDE_avail_cAMP_deg">
        <math xmlns="http://www.w3.org/1998/Math/MathML">        
          <apply>
            <divide/>
            <apply>
              <times/>
              <apply>
                <times/>
                <cn> 0.0016605387831627259 </cn>
                <ci> PDE </ci>
              </apply>
              <ci> Ki_cAMP_deg </ci>
            </apply>
            <apply>
              <plus/>
              <ci> Ki_cAMP_deg </ci>
              <ci> IBMX_cAMP_deg </ci>
            </apply>
          </apply>
        </math>
            </assignmentRule>
      <assignmentRule variable="IBMX_cAMP_deg">
        <math xmlns="http://www.w3.org/1998/Math/MathML">        
          <apply>
            <times/>
            <ci> IBMX_stim_cAMP_deg </ci>
            <apply>
              <gt/>
              <ci> t </ci>
              <ci> t_IBMX_cAMP_deg </ci>
            </apply>
          </apply>
        </math>
            </assignmentRule>
      <assignmentRule variable="Vmax_AKAR_phos">
        <math xmlns="http://www.w3.org/1998/Math/MathML">        
          <apply>
            <times/>
            <ci> kcat_AKAR_phos </ci>
            <ci> PKAC </ci>
          </apply>
        </math>
            </assignmentRule>
    </listOfRules>
    <listOfReactions>
      <reaction fast="false" id="cAMP_synth" name="cAMP_synth" reversible="true">
        <listOfProducts>
          <speciesReference constant="true" id="cAMP_synth_cAMPp" species="cAMP" stoichiometry="1"/>
        </listOfProducts>
        <listOfModifiers>
          <modifierSpeciesReference species="AC"/>
        </listOfModifiers>
        <kineticLaw>
          <math xmlns="http://www.w3.org/1998/Math/MathML">          
            <apply>
              <times/>
              <apply>
                <divide/>
                <apply>
                  <plus/>
                  <apply>
                    <plus/>
                    <apply>
                      <plus/>
                      <apply>
                        <times/>
                        <apply>
                          <times/>
                          <cn> 602.214179 </cn>
                          <apply>
                            <power/>
                            <ci> ATP_cAMP_synth </ci>
                            <cn> 2 </cn>
                          </apply>
                        </apply>
                        <ci> Vmax_cAMP_synth </ci>
                      </apply>
                      <apply>
                        <times/>
                        <apply>
                          <times/>
                          <apply>
                            <times/>
                            <cn> 602.214179 </cn>
                            <ci> ATP_cAMP_synth </ci>
                          </apply>
                          <ci> Km_Iso_cAMP_synth </ci>
                        </apply>
                        <ci> Vmax_cAMP_synth </ci>
                      </apply>
                    </apply>
                    <apply>
                      <times/>
                      <apply>
                        <times/>
                        <cn> 602.214179 </cn>
                        <apply>
                          <power/>
                          <ci> ATP_cAMP_synth </ci>
                          <cn> 2 </cn>
                        </apply>
                      </apply>
                      <ci> Vmax_Iso_cAMP_synth </ci>
                    </apply>
                  </apply>
                  <apply>
                    <times/>
                    <apply>
                      <times/>
                      <apply>
                        <times/>
                        <cn> 602.214179 </cn>
                        <ci> ATP_cAMP_synth </ci>
                      </apply>
                      <ci> Km_cAMP_synth </ci>
                    </apply>
                    <ci> Vmax_Iso_cAMP_synth </ci>
                  </apply>
                </apply>
                <apply>
                  <plus/>
                  <apply>
                    <plus/>
                    <apply>
                      <plus/>
                      <apply>
                        <power/>
                        <ci> ATP_cAMP_synth </ci>
                        <cn> 2 </cn>
                      </apply>
                      <apply>
                        <times/>
                        <ci> ATP_cAMP_synth </ci>
                        <ci> Km_cAMP_synth </ci>
                      </apply>
                    </apply>
                    <apply>
                      <times/>
                      <ci> ATP_cAMP_synth </ci>
                      <ci> Km_Iso_cAMP_synth </ci>
                    </apply>
                  </apply>
                  <apply>
                    <times/>
                    <ci> Km_cAMP_synth </ci>
                    <ci> Km_Iso_cAMP_synth </ci>
                  </apply>
                </apply>
              </apply>
              <ci> cytosol </ci>
            </apply>
          </math>
                </kineticLaw>
      </reaction>
      <reaction fast="false" id="PKA_act" name="PKA_act" reversible="true">
        <listOfReactants>
          <speciesReference constant="true" id="PKA_act_A2RCr" species="A2RC" stoichiometry="1"/>
        </listOfReactants>
        <listOfProducts>
          <speciesReference constant="true" id="PKA_act_A2Rp" species="A2R" stoichiometry="1"/>
          <speciesReference constant="true" id="PKA_act_PKACp" species="PKAC" stoichiometry="1"/>
        </listOfProducts>
        <kineticLaw>
          <math xmlns="http://www.w3.org/1998/Math/MathML">          
            <apply>
              <times/>
              <apply>
                <minus/>
                <apply>
                  <times/>
                  <ci> A2RC </ci>
                  <ci> Kf_PKA_act </ci>
                </apply>
                <apply>
                  <times/>
                  <apply>
                    <times/>
                    <ci> A2R </ci>
                    <ci> Kr_PKA_act </ci>
                  </apply>
                  <ci> PKAC </ci>
                </apply>
              </apply>
              <ci> cytosol </ci>
            </apply>
          </math>
                </kineticLaw>
      </reaction>
      <reaction fast="false" id="cAMP_deg" name="cAMP_deg" reversible="true">
        <listOfReactants>
          <speciesReference constant="true" id="cAMP_deg_cAMPr" species="cAMP" stoichiometry="1"/>
        </listOfReactants>
        <listOfModifiers>
          <modifierSpeciesReference species="PDE"/>
        </listOfModifiers>
        <kineticLaw>
          <math xmlns="http://www.w3.org/1998/Math/MathML">          
            <apply>
              <times/>
              <apply>
                <divide/>
                <apply>
                  <times/>
                  <apply>
                    <times/>
                    <cn> 0.0016605387831627257 </cn>
                    <ci> Vmax_cAMP_deg </ci>
                  </apply>
                  <ci> cAMP </ci>
                </apply>
                <apply>
                  <plus/>
                  <apply>
                    <times/>
                    <cn> 0.0016605387831627259 </cn>
                    <ci> Km_cAMP_deg </ci>
                  </apply>
                  <apply>
                    <times/>
                    <cn> 0.0016605387831627259 </cn>
                    <ci> cAMP </ci>
                  </apply>
                </apply>
              </apply>
              <ci> cytosol </ci>
            </apply>
          </math>
                </kineticLaw>
      </reaction>
      <reaction fast="false" id="PKA_bind1" name="PKA_bind1" reversible="true">
        <listOfReactants>
          <speciesReference constant="true" id="PKA_bind1_RCr" species="RC" stoichiometry="1"/>
          <speciesReference constant="true" id="PKA_bind1_cAMPr" species="cAMP" stoichiometry="1"/>
        </listOfReactants>
        <listOfProducts>
          <speciesReference constant="true" id="PKA_bind1_ARCp" species="ARC" stoichiometry="1"/>
        </listOfProducts>
        <kineticLaw>
          <math xmlns="http://www.w3.org/1998/Math/MathML">          
            <apply>
              <times/>
              <apply>
                <plus/>
                <apply>
                  <minus/>
                  <apply>
                    <times/>
                    <ci> ARC </ci>
                    <ci> Kr_PKA_bind1 </ci>
                  </apply>
                </apply>
                <apply>
                  <times/>
                  <apply>
                    <times/>
                    <ci> Kf_PKA_bind1 </ci>
                    <ci> RC </ci>
                  </apply>
                  <ci> cAMP </ci>
                </apply>
              </apply>
              <ci> cytosol </ci>
            </apply>
          </math>
                </kineticLaw>
      </reaction>
      <reaction fast="false" id="AKAR_dephos" name="AKAR_dephos" reversible="true">
        <listOfReactants>
          <speciesReference constant="true" id="AKAR_dephos_AKARpr" species="AKARp" stoichiometry="1"/>
        </listOfReactants>
        <listOfProducts>
          <speciesReference constant="true" id="AKAR_dephos_AKARp" species="AKAR" stoichiometry="1"/>
        </listOfProducts>
        <kineticLaw>
          <math xmlns="http://www.w3.org/1998/Math/MathML">          
            <apply>
              <times/>
              <apply>
                <times/>
                <apply>
                  <times/>
                  <ci> AKARp </ci>
                  <ci> PPase_AKAR_dephos </ci>
                </apply>
                <ci> kcat_AKAR_dephos </ci>
              </apply>
              <ci> cytosol </ci>
            </apply>
          </math>
                </kineticLaw>
      </reaction>
      <reaction fast="false" id="PKA_bind2" name="PKA_bind2" reversible="true">
        <listOfReactants>
          <speciesReference constant="true" id="PKA_bind2_ARCr" species="ARC" stoichiometry="1"/>
          <speciesReference constant="true" id="PKA_bind2_cAMPr" species="cAMP" stoichiometry="1"/>
        </listOfReactants>
        <listOfProducts>
          <speciesReference constant="true" id="PKA_bind2_A2RCp" species="A2RC" stoichiometry="1"/>
        </listOfProducts>
        <kineticLaw>
          <math xmlns="http://www.w3.org/1998/Math/MathML">          
            <apply>
              <times/>
              <apply>
                <plus/>
                <apply>
                  <minus/>
                  <apply>
                    <times/>
                    <ci> A2RC </ci>
                    <ci> Kr_PKA_bind2 </ci>
                  </apply>
                </apply>
                <apply>
                  <times/>
                  <apply>
                    <times/>
                    <ci> ARC </ci>
                    <ci> Kf_PKA_bind2 </ci>
                  </apply>
                  <ci> cAMP </ci>
                </apply>
              </apply>
              <ci> cytosol </ci>
            </apply>
          </math>
                </kineticLaw>
      </reaction>
      <reaction fast="false" id="ICUE_bind" name="ICUE_bind" reversible="true">
        <listOfReactants>
          <speciesReference constant="true" id="ICUE_bind_ICUEr" species="ICUE" stoichiometry="1"/>
          <speciesReference constant="true" id="ICUE_bind_cAMPr" species="cAMP" stoichiometry="1"/>
        </listOfReactants>
        <listOfProducts>
          <speciesReference constant="true" id="ICUE_bind_ICUE_cAMPp" species="ICUE_cAMP" stoichiometry="1"/>
        </listOfProducts>
        <kineticLaw>
          <math xmlns="http://www.w3.org/1998/Math/MathML">          
            <apply>
              <times/>
              <apply>
                <plus/>
                <apply>
                  <minus/>
                  <apply>
                    <times/>
                    <ci> ICUE_cAMP </ci>
                    <ci> Kr_ICUE_bind </ci>
                  </apply>
                </apply>
                <apply>
                  <times/>
                  <apply>
                    <times/>
                    <ci> ICUE </ci>
                    <ci> Kf_ICUE_bind </ci>
                  </apply>
                  <ci> cAMP </ci>
                </apply>
              </apply>
              <ci> cytosol </ci>
            </apply>
          </math>
                </kineticLaw>
      </reaction>
      <reaction fast="false" id="AKAR_phos" name="AKAR_phos" reversible="true">
        <listOfReactants>
          <speciesReference constant="true" id="AKAR_phos_AKARr" species="AKAR" stoichiometry="1"/>
        </listOfReactants>
        <listOfProducts>
          <speciesReference constant="true" id="AKAR_phos_AKARpp" species="AKARp" stoichiometry="1"/>
        </listOfProducts>
        <listOfModifiers>
          <modifierSpeciesReference species="PKAC"/>
        </listOfModifiers>
        <kineticLaw>
          <math xmlns="http://www.w3.org/1998/Math/MathML">          
            <apply>
              <times/>
              <apply>
                <divide/>
                <apply>
                  <times/>
                  <apply>
                    <times/>
                    <cn> 0.0016605387831627257 </cn>
                    <ci> AKAR </ci>
                  </apply>
                  <ci> Vmax_AKAR_phos </ci>
                </apply>
                <apply>
                  <plus/>
                  <apply>
                    <times/>
                    <cn> 0.0016605387831627259 </cn>
                    <ci> AKAR </ci>
                  </apply>
                  <apply>
                    <times/>
                    <cn> 0.0016605387831627259 </cn>
                    <ci> Km_AKAR_phos </ci>
                  </apply>
                </apply>
              </apply>
              <ci> cytosol </ci>
            </apply>
          </math>
                </kineticLaw>
      </reaction>
    </listOfReactions>
  </model>
</sbml>